{
    "ocid": "ocds-f5kvwu-2023_PWD_34308_1",
    "id": 1,
    "date": "2024-11-28",
    "fiscalYear": "2023-2024",
    "mainProcurementCategory": "Works",
    "bidOpeningDate": "08-Dec-2023 11:00 AM",
    "tenderValueAmount": "1,57,09,000",
    "tender": [
        {
            "id": "2023_PWD_34308_1",
            "title": "Construction of Road from Barapujia Kumargaon Road to Jarabari",
            "description": "Construction of Road from Barapujia Kumargaon Road to Jarabari",
            "datePublished": "01-Dec-2023 10:00 AM",
            "contractType": "Item Rate",
            "procurementMethod": "Open Tender",
            "mainProcuremenCategory": "Works",
            "value": [
                {
                    "amount": "1,57,09,000",
                    "currency": "INR"
                }
            ],
            "bidOpeing": [
                {
                    "date": "08-Dec-2023 11:00 AM"
                }
            ]
        }
    ]
}