{
    "ocid": "ocds-f5kvwu-2023_PWD_34775_1",
    "id": 1,
    "date": "2024-11-28",
    "fiscalYear": "2023-2024",
    "mainProcurementCategory": "Works",
    "bidOpeningDate": "02-Jan-2024 11:00 AM",
    "tenderValueAmount": "3,72,69,000",
    "tender": [
        {
            "id": "2023_PWD_34775_1",
            "title": "Maint/MMPPNA/2023-24/82",
            "description": "Maint/MMPPNA/2023-24/82",
            "datePublished": "18-Dec-2023 02:00 PM",
            "contractType": "Item Rate",
            "procurementMethod": "Open Tender",
            "mainProcuremenCategory": "Works",
            "value": [
                {
                    "amount": "3,72,69,000",
                    "currency": "INR"
                }
            ],
            "bidOpeing": [
                {
                    "date": "02-Jan-2024 11:00 AM"
                }
            ]
        }
    ]
}