{
    "ocid": "ocds-f5kvwu-2023_PCCF_33239_1",
    "id": 1,
    "date": "2024-11-28",
    "fiscalYear": "2023-2024",
    "mainProcurementCategory": "Services",
    "bidOpeningDate": "21-Nov-2023 04:00 PM",
    "tenderValueAmount": "18,38,326",
    "tender": [
        {
            "id": "2023_PCCF_33239_1",
            "title": "DOCUMENTATION AND PUBLICATION OF COFFEE TABLE BOOK",
            "description": "DOCUMENTATION AND PUBLICATION OF COFFEE TABLE BOOK",
            "datePublished": "21-Oct-2023 09:00 AM",
            "contractType": "Percentage",
            "procurementMethod": "Open Tender",
            "mainProcuremenCategory": "Services",
            "value": [
                {
                    "amount": "18,38,326",
                    "currency": "INR"
                }
            ],
            "bidOpeing": [
                {
                    "date": "21-Nov-2023 04:00 PM"
                }
            ]
        }
    ]
}