{
    "ocid": "ocds-f5kvwu-2024_GMC_36047_3",
    "id": 1,
    "date": "2024-11-28",
    "fiscalYear": "2023-2024",
    "mainProcurementCategory": "Works",
    "bidOpeningDate": "28-Feb-2024 03:00 PM",
    "tenderValueAmount": "37,50,000",
    "tender": [
        {
            "id": "2024_GMC_36047_3",
            "title": "Improvement of a bye lane at railway Colony Road adjacent to Refinery channel W/no.53",
            "description": "Improvement of a bye lane at railway Colony Road adjacent to Refinery channel W/no.53",
            "datePublished": "08-Feb-2024 02:00 PM",
            "contractType": "Lump-sum",
            "procurementMethod": "Open Tender",
            "mainProcuremenCategory": "Works",
            "value": [
                {
                    "amount": "37,50,000",
                    "currency": "INR"
                }
            ],
            "bidOpeing": [
                {
                    "date": "28-Feb-2024 03:00 PM"
                }
            ]
        }
    ]
}