{
    "ocid": "ocds-f5kvwu-2024_BoTC_35370_1",
    "id": 1,
    "date": "2024-11-28",
    "fiscalYear": "2023-2024",
    "mainProcurementCategory": "Works",
    "bidOpeningDate": "29-Jan-2024 03:30 PM",
    "tenderValueAmount": "22,00,000",
    "tender": [
        {
            "id": "2024_BoTC_35370_1",
            "title": "Extension of office building of Fakiragram Municipal Board Office",
            "description": "Extension of office building of Fakiragram Municipal Board Office",
            "datePublished": "10-Jan-2024 03:30 PM",
            "contractType": "Works",
            "procurementMethod": "Open Tender",
            "mainProcuremenCategory": "Works",
            "value": [
                {
                    "amount": "22,00,000",
                    "currency": "INR"
                }
            ],
            "bidOpeing": [
                {
                    "date": "29-Jan-2024 03:30 PM"
                }
            ]
        }
    ]
}