{
    "ocid": "ocds-f5kvwu-2024_PWD_35757_1",
    "id": 1,
    "date": "2024-11-28",
    "fiscalYear": "2023-2024",
    "mainProcurementCategory": "Works",
    "bidOpeningDate": "07-Feb-2024 02:30 PM",
    "tenderValueAmount": "3,10,31,000",
    "tender": [
        {
            "id": "2024_PWD_35757_1",
            "title": "Rupnagar Birubari Road-Fl Mitigation",
            "description": "Rupnagar Birubari Road-Fl Mitigation",
            "datePublished": "29-Jan-2024 01:00 PM",
            "contractType": "Item Rate",
            "procurementMethod": "Open Tender",
            "mainProcuremenCategory": "Works",
            "value": [
                {
                    "amount": "3,10,31,000",
                    "currency": "INR"
                }
            ],
            "bidOpeing": [
                {
                    "date": "07-Feb-2024 02:30 PM"
                }
            ]
        }
    ]
}